viper/__init__.py
viper/ast.py
viper/common.py
viper/errors.py
viper/lexer.py
viper/objects.py
viper/parser.py
viper/runner.py
viper/scope.py
viper/exts/discord.py
viper/lib/__init__.py
viper/lib/_builtins.py
viper/lib/files.py
viper/lib/json.py
viper/lib/random.py
viper/lib/regex.py
viper/lib/requests.py
viper_lang-1.0.0.dist-info/LICENSE
viper_lang-1.0.0.dist-info/METADATA
viper_lang-1.0.0.dist-info/WHEEL
viper_lang-1.0.0.dist-info/top_level.txt
viper_lang-1.0.0.dist-info/RECORD
