Metadata-Version: 2.1
Name: viper-lang
Version: 1.0.0
Summary: a simple, easy to understand language with easy integration capabilities.
Home-page: https://github.com/IAmTomahawkx/viper-lang
Author: IAmTomahawkx
Author-email: iamtomahawkx@gmail.com
License: MIT
Project-URL: Issue tracker, https://github.com/IAmTomahawkx/viper-lang/issues
Platform: UNKNOWN
Classifier: Development Status :: 4 - Beta
Classifier: License :: OSI Approved :: MIT License
Classifier: Intended Audience :: Developers
Classifier: Natural Language :: English
Classifier: Operating System :: OS Independent
Classifier: Programming Language :: Python :: 3.6
Classifier: Programming Language :: Python :: 3.7
Classifier: Programming Language :: Python :: 3.8
Classifier: Programming Language :: Python :: 3.9
Classifier: Topic :: Internet
Classifier: Topic :: Software Development :: Libraries
Classifier: Topic :: Software Development :: Libraries :: Python Modules
Classifier: Topic :: Utilities
Requires-Python: >=3.6.0
Requires-Dist: sly
